[
  {
    "ContainingType": "NguyenMinhTai_2280602802.Controllers.ProductApiController",
    "Method": "GetProducts",
    "RelativePath": "api/ProductApi",
    "HttpMethod": "GET",
    "IsController": true,
    "Order": 0,
    "Parameters": [],
    "ReturnTypes": []
  },
  {
    "ContainingType": "NguyenMinhTai_2280602802.Controllers.ProductApiController",
    "Method": "AddProduct",
    "RelativePath": "api/ProductApi",
    "HttpMethod": "POST",
    "IsController": true,
    "Order": 0,
    "Parameters": [
      {
        "Name": "product",
        "Type": "NguyenMinhTai_2280602802.Model.Product",
        "IsRequired": true
      }
    ],
    "ReturnTypes": []
  },
  {
    "ContainingType": "NguyenMinhTai_2280602802.Controllers.ProductApiController",
    "Method": "GetProductById",
    "RelativePath": "api/ProductApi/{id}",
    "HttpMethod": "GET",
    "IsController": true,
    "Order": 0,
    "Parameters": [
      {
        "Name": "id",
        "Type": "System.Int32",
        "IsRequired": true
      }
    ],
    "ReturnTypes": []
  },
  {
    "ContainingType": "NguyenMinhTai_2280602802.Controllers.ProductApiController",
    "Method": "UpdateProduct",
    "RelativePath": "api/ProductApi/{id}",
    "HttpMethod": "PUT",
    "IsController": true,
    "Order": 0,
    "Parameters": [
      {
        "Name": "id",
        "Type": "System.Int32",
        "IsRequired": true
      },
      {
        "Name": "product",
        "Type": "NguyenMinhTai_2280602802.Model.Product",
        "IsRequired": true
      }
    ],
    "ReturnTypes": []
  },
  {
    "ContainingType": "NguyenMinhTai_2280602802.Controllers.ProductApiController",
    "Method": "DeleteProduct",
    "RelativePath": "api/ProductApi/{id}",
    "HttpMethod": "DELETE",
    "IsController": true,
    "Order": 0,
    "Parameters": [
      {
        "Name": "id",
        "Type": "System.Int32",
        "IsRequired": true
      }
    ],
    "ReturnTypes": []
  }
]